{"cameraMode":{"drawMode":0,"name":"Shaded","section":"Shading Mode"},"sceneLighting":true,"audioPlay":false,"sceneViewState":{"showFog":true,"showMaterialUpdate":false,"showSkybox":true,"showFlares":true,"showImageEffects":true,"showParticleSystems":true},"in2DMode":false,"pivot":{"x":130.87680053710938,"y":4.210048675537109,"z":128.62100219726563},"rotation":{"x":0.12162259221076966,"y":0.08108304440975189,"z":-0.010910656303167344,"w":0.9892857074737549},"size":118.51947021484375,"orthographic":false}